{
  "generatedAt": "2026-07-15T07:49:56.758Z",
  "fields": {
    "society": "社会",
    "economy": "经济",
    "entertainment": "娱乐"
  },
  "feed": [
    {
      "id": "evt-00000000",
      "title": "龙凤胎哥哥上国防科大妹妹上北大",
      "category": "society",
      "hotScore": 0.85,
      "freshness": 0.9999,
      "crossSource": 0.6309,
      "totalScore": 0.8293,
      "sources": [
        {
          "channel": "toutiao",
          "rank": 1,
          "hot": 59611744,
          "url": "https://www.toutiao.com/trending/7662593488202612772/"
        }
      ],
      "summary": "",
      "url": "https://www.toutiao.com/trending/7662593488202612772/"
    },
    {
      "id": "evt-75000000",
      "title": "打虎！75岁正部蔡赴朝被查",
      "category": "society",
      "hotScore": 0.8075,
      "freshness": 0.9999,
      "crossSource": 0.6309,
      "totalScore": 0.8123,
      "sources": [
        {
          "channel": "toutiao",
          "rank": 2,
          "hot": 53938937,
          "url": "https://www.toutiao.com/trending/7662630430185357353/"
        }
      ],
      "summary": "",
      "url": "https://www.toutiao.com/trending/7662630430185357353/"
    },
    {
      "id": "evt-64000000",
      "title": "新华社分析64队世界杯，从设想到现实还有多远",
      "category": "society",
      "hotScore": 0.8075,
      "freshness": 0.9999,
      "crossSource": 0.6309,
      "totalScore": 0.8123,
      "sources": [
        {
          "channel": "thepaper",
          "rank": 2,
          "hot": 0,
          "url": "https://www.thepaper.cn/newsDetail_forward_33584231"
        }
      ],
      "summary": "",
      "url": "https://www.thepaper.cn/newsDetail_forward_33584231"
    },
    {
      "id": "evt-20000000",
      "title": "西班牙2-0淘汰法国，率先挺进世界杯决赛",
      "category": "society",
      "hotScore": 0.765,
      "freshness": 0.9999,
      "crossSource": 0.6309,
      "totalScore": 0.7953,
      "sources": [
        {
          "channel": "thepaper",
          "rank": 3,
          "hot": 0,
          "url": "https://www.thepaper.cn/newsDetail_forward_33587688"
        }
      ],
      "summary": "",
      "url": "https://www.thepaper.cn/newsDetail_forward_33587688"
    },
    {
      "id": "evt-10000000",
      "title": "中芯国际与嘉楠科技合作14nm矿机芯片，知情人士：能否量产要看行情",
      "category": "economy",
      "hotScore": 0.9,
      "freshness": 1,
      "crossSource": 0.6309,
      "totalScore": 0.8493,
      "sources": [
        {
          "channel": "36kr",
          "rank": 1,
          "hot": 0,
          "url": ""
        }
      ],
      "summary": "有消息称，中芯国际与嘉楠科技合作的14nm矿机芯片已完成测试，将在今年二季度量产出货。对此，知情人士称，双方合作始于2019年年底，但能否量产要看行情。据悉，中芯国际数次尝试进入矿机行业，但受行情拖累一直未有实质进展。（财联社）",
      "url": ""
    },
    {
      "id": "evt-5g000000",
      "title": "三大运营商年内推出5G消息",
      "category": "economy",
      "hotScore": 0.855,
      "freshness": 1,
      "crossSource": 0.6309,
      "totalScore": 0.8313,
      "sources": [
        {
          "channel": "36kr",
          "rank": 2,
          "hot": 0,
          "url": ""
        }
      ],
      "summary": "三大运营商计划在年内推出升级版短信服务5G消息。5G消息的特点：①打破传统短信长度限制，实现文、图、音视频、表情等融合；②支持在线支付、在线和离线消息；③不加好友就能随时发起群发、群聊。业内人士指出，5G消息可能按流量计费，价格有望比目前的短信和微信更优惠。（央视新闻）",
      "url": ""
    },
    {
      "id": "evt-take0000",
      "title": "欧洲在线订餐服务Takeaway.com：外卖订单开始强劲复苏",
      "category": "economy",
      "hotScore": 0.81,
      "freshness": 1,
      "crossSource": 0.6309,
      "totalScore": 0.8133,
      "sources": [
        {
          "channel": "36kr",
          "rank": 3,
          "hot": 0,
          "url": ""
        }
      ],
      "summary": "据外媒报道，随着闭门不出的消费者厌倦了在家里做饭或寻求改变他们的日常生活，更多的人开始将点外卖作为一种改变局面的方式。欧洲最大的在线订餐服务之一Takeaway.com称，外卖订单已开始强劲复苏。而分析师表示，这种复苏是“I型复苏”，而不是“V型复苏”。（腾讯科技）",
      "url": ""
    },
    {
      "id": "evt-2026gdp6",
      "title": "2026 年上半年 GDP 695704 亿元，同比增长 4.7%，如何解读这一数据？",
      "category": "economy",
      "hotScore": 0.7125,
      "freshness": 0.9999,
      "crossSource": 0.6309,
      "totalScore": 0.7743,
      "sources": [
        {
          "channel": "zhihu",
          "rank": 2,
          "hot": 0,
          "url": ""
        }
      ],
      "summary": "",
      "url": ""
    },
    {
      "id": "evt-87000000",
      "title": "87版《红楼梦》刘姥姥扮演者去世",
      "category": "society",
      "hotScore": 0.72,
      "freshness": 0.9999,
      "crossSource": 0.6309,
      "totalScore": 0.7773,
      "sources": [
        {
          "channel": "baidu",
          "rank": 3,
          "hot": 0,
          "url": "https://m.baidu.com/s?word=87%E7%89%88%E3%80%8A%E7%BA%A2%E6%A5%BC%E6%A2%A6%E3%80%8B%E5%88%98%E5%A7%A5%E5%A7%A5%E6%89%AE%E6%BC%94%E8%80%85%E5%8E%BB%E4%B8%96&sa=fyb_news"
        }
      ],
      "summary": "",
      "url": "https://m.baidu.com/s?word=87%E7%89%88%E3%80%8A%E7%BA%A2%E6%A5%BC%E6%A2%A6%E3%80%8B%E5%88%98%E5%A7%A5%E5%A7%A5%E6%89%AE%E6%BC%94%E8%80%85%E5%8E%BB%E4%B8%96&sa=fyb_news"
    },
    {
      "id": "evt-40000000",
      "title": "上线一周年4000万人申领",
      "category": "society",
      "hotScore": 0.6375,
      "freshness": 0.9999,
      "crossSource": 0.6309,
      "totalScore": 0.7443,
      "sources": [
        {
          "channel": "toutiao",
          "rank": 6,
          "hot": 36156350,
          "url": "https://www.toutiao.com/trending/7662045803342970931/"
        }
      ],
      "summary": "",
      "url": "https://www.toutiao.com/trending/7662045803342970931/"
    },
    {
      "id": "evt-20260000",
      "title": "2026 年美加墨世界杯半决赛，英格兰 vs 阿根廷，你看好谁能取胜？",
      "category": "society",
      "hotScore": 0.6375,
      "freshness": 0.9999,
      "crossSource": 0.6309,
      "totalScore": 0.7443,
      "sources": [
        {
          "channel": "zhihu",
          "rank": 4,
          "hot": 0,
          "url": ""
        }
      ],
      "summary": "",
      "url": ""
    },
    {
      "id": "evt-3d000000",
      "title": "好未来《熊猫博士》3D动画片登陆央视少儿频道",
      "category": "society",
      "hotScore": 0.63,
      "freshness": 1,
      "crossSource": 0.6309,
      "totalScore": 0.7413,
      "sources": [
        {
          "channel": "36kr",
          "rank": 7,
          "hot": 0,
          "url": ""
        }
      ],
      "summary": "36氪获悉，自4月9日起，中央电视台少儿频道携手好未来旗下教育品牌熊猫博士上线3D系列动画片《熊猫博士》。与此同时，《熊猫博士》3D动画片也在美国、加拿大、俄罗斯、意大利等多个国家、地区陆续发行，并登陆Discovery探索频道等多个世界知名节目。",
      "url": ""
    },
    {
      "id": "evt-18000000",
      "title": "租了18年房 退租被要求“恢复如新”",
      "category": "society",
      "hotScore": 0.6,
      "freshness": 0.9999,
      "crossSource": 0.6309,
      "totalScore": 0.7293,
      "sources": [
        {
          "channel": "baidu",
          "rank": 6,
          "hot": 0,
          "url": "https://m.baidu.com/s?word=%E7%A7%9F%E4%BA%8618%E5%B9%B4%E6%88%BF+%E9%80%80%E7%A7%9F%E8%A2%AB%E8%A6%81%E6%B1%82%E2%80%9C%E6%81%A2%E5%A4%8D%E5%A6%82%E6%96%B0%E2%80%9D&sa=fyb_news"
        }
      ],
      "summary": "",
      "url": "https://m.baidu.com/s?word=%E7%A7%9F%E4%BA%8618%E5%B9%B4%E6%88%BF+%E9%80%80%E7%A7%9F%E8%A2%AB%E8%A6%81%E6%B1%82%E2%80%9C%E6%81%A2%E5%A4%8D%E5%A6%82%E6%96%B0%E2%80%9D&sa=fyb_news"
    },
    {
      "id": "evt-10200000",
      "title": "国台办回应“10至20年间逐渐统一”",
      "category": "society",
      "hotScore": 0.595,
      "freshness": 0.9999,
      "crossSource": 0.6309,
      "totalScore": 0.7273,
      "sources": [
        {
          "channel": "toutiao",
          "rank": 7,
          "hot": 32715619,
          "url": "https://www.toutiao.com/trending/7662314127614296115/"
        }
      ],
      "summary": "",
      "url": "https://www.toutiao.com/trending/7662314127614296115/"
    },
    {
      "id": "evt-36000000",
      "title": "身家飙升至 360 亿美元，为什么梁文锋能超越奥特曼和达里奥成全球 AI 大模型创始人首富？",
      "category": "society",
      "hotScore": 0.5625,
      "freshness": 0.9999,
      "crossSource": 0.6309,
      "totalScore": 0.7143,
      "sources": [
        {
          "channel": "zhihu",
          "rank": 6,
          "hot": 0,
          "url": ""
        }
      ],
      "summary": "",
      "url": ""
    }
  ]
}