{
  "generatedAt": "2026-07-14T01:25:17.603Z",
  "fields": {
    "society": "社会",
    "economy": "经济",
    "entertainment": "娱乐"
  },
  "feed": [
    {
      "id": "evt-00000000",
      "title": "伊朗称袭击美国海军第五舰队司令部",
      "category": "society",
      "hotScore": 0.72,
      "freshness": 1,
      "crossSource": 1,
      "totalScore": 0.888,
      "sources": [
        {
          "channel": "toutiao",
          "rank": 13,
          "hot": 8371470,
          "url": "https://www.toutiao.com/trending/7661886519921573894/"
        },
        {
          "channel": "baidu",
          "rank": 3,
          "hot": 0,
          "url": "https://m.baidu.com/s?word=%E4%BC%8A%E6%9C%97%E7%A7%B0%E8%A2%AD%E5%87%BB%E7%BE%8E%E5%9B%BD%E6%B5%B7%E5%86%9B%E7%AC%AC%E4%BA%94%E8%88%B0%E9%98%9F%E5%8F%B8%E4%BB%A4%E9%83%A8&sa=fyb_news"
        }
      ],
      "summary": "",
      "url": "https://www.toutiao.com/trending/7661886519921573894/"
    },
    {
      "id": "evt-vs000000",
      "title": "法国vs西班牙半决赛前将进行默哀",
      "category": "society",
      "hotScore": 0.64,
      "freshness": 1,
      "crossSource": 1,
      "totalScore": 0.856,
      "sources": [
        {
          "channel": "toutiao",
          "rank": 9,
          "hot": 12488766,
          "url": "https://www.toutiao.com/trending/7661965559416225811/"
        },
        {
          "channel": "baidu",
          "rank": 5,
          "hot": 0,
          "url": "https://m.baidu.com/s?word=%E6%B3%95%E5%9B%BDvs%E8%A5%BF%E7%8F%AD%E7%89%99%E5%8D%8A%E5%86%B3%E8%B5%9B%E5%89%8D%E5%B0%86%E8%BF%9B%E8%A1%8C%E9%BB%98%E5%93%80&sa=fyb_news"
        }
      ],
      "summary": "",
      "url": "https://www.toutiao.com/trending/7661965559416225811/"
    },
    {
      "id": "evt-30000000",
      "title": "消防员抱出3个月婴儿时手都抖了",
      "category": "society",
      "hotScore": 0.85,
      "freshness": 1,
      "crossSource": 0.6309,
      "totalScore": 0.8293,
      "sources": [
        {
          "channel": "toutiao",
          "rank": 1,
          "hot": 27794261,
          "url": "https://www.toutiao.com/trending/7661138997096267795/"
        }
      ],
      "summary": "",
      "url": "https://www.toutiao.com/trending/7661138997096267795/"
    },
    {
      "id": "evt-20260000",
      "title": "习近平将出席2026世界人工智能大会暨人工智能全球治理高级别会议开幕式并发表主旨讲话",
      "category": "society",
      "hotScore": 0.85,
      "freshness": 1,
      "crossSource": 0.6309,
      "totalScore": 0.8293,
      "sources": [
        {
          "channel": "thepaper",
          "rank": 1,
          "hot": 0,
          "url": "https://www.thepaper.cn/newsDetail_forward_33574538"
        }
      ],
      "summary": "",
      "url": "https://www.thepaper.cn/newsDetail_forward_33574538"
    },
    {
      "id": "evt-10000000",
      "title": "中芯国际与嘉楠科技合作14nm矿机芯片，知情人士：能否量产要看行情",
      "category": "economy",
      "hotScore": 0.9,
      "freshness": 1,
      "crossSource": 0.6309,
      "totalScore": 0.8493,
      "sources": [
        {
          "channel": "36kr",
          "rank": 1,
          "hot": 0,
          "url": ""
        }
      ],
      "summary": "有消息称，中芯国际与嘉楠科技合作的14nm矿机芯片已完成测试，将在今年二季度量产出货。对此，知情人士称，双方合作始于2019年年底，但能否量产要看行情。据悉，中芯国际数次尝试进入矿机行业，但受行情拖累一直未有实质进展。（财联社）",
      "url": ""
    },
    {
      "id": "evt-5g000000",
      "title": "三大运营商年内推出5G消息",
      "category": "economy",
      "hotScore": 0.855,
      "freshness": 1,
      "crossSource": 0.6309,
      "totalScore": 0.8313,
      "sources": [
        {
          "channel": "36kr",
          "rank": 2,
          "hot": 0,
          "url": ""
        }
      ],
      "summary": "三大运营商计划在年内推出升级版短信服务5G消息。5G消息的特点：①打破传统短信长度限制，实现文、图、音视频、表情等融合；②支持在线支付、在线和离线消息；③不加好友就能随时发起群发、群聊。业内人士指出，5G消息可能按流量计费，价格有望比目前的短信和微信更优惠。（央视新闻）",
      "url": ""
    },
    {
      "id": "evt-take0000",
      "title": "欧洲在线订餐服务Takeaway.com：外卖订单开始强劲复苏",
      "category": "economy",
      "hotScore": 0.81,
      "freshness": 1,
      "crossSource": 0.6309,
      "totalScore": 0.8133,
      "sources": [
        {
          "channel": "36kr",
          "rank": 3,
          "hot": 0,
          "url": ""
        }
      ],
      "summary": "据外媒报道，随着闭门不出的消费者厌倦了在家里做饭或寻求改变他们的日常生活，更多的人开始将点外卖作为一种改变局面的方式。欧洲最大的在线订餐服务之一Takeaway.com称，外卖订单已开始强劲复苏。而分析师表示，这种复苏是“I型复苏”，而不是“V型复苏”。（腾讯科技）",
      "url": ""
    },
    {
      "id": "evt-20000000",
      "title": "放射科主任伙同女友受贿2392万获刑",
      "category": "society",
      "hotScore": 0.7225,
      "freshness": 1,
      "crossSource": 0.6309,
      "totalScore": 0.7783,
      "sources": [
        {
          "channel": "toutiao",
          "rank": 4,
          "hot": 20590495,
          "url": "https://www.toutiao.com/trending/7662170851210497574/"
        }
      ],
      "summary": "",
      "url": "https://www.toutiao.com/trending/7662170851210497574/"
    },
    {
      "id": "evt-icm20260",
      "title": "网传 ICM 2026 菲尔兹奖名单在网页前端泄露，王虹、邓煜在获奖者讲座名单中，如何看待这一信息？",
      "category": "society",
      "hotScore": 0.675,
      "freshness": 1,
      "crossSource": 0.6309,
      "totalScore": 0.7593,
      "sources": [
        {
          "channel": "zhihu",
          "rank": 3,
          "hot": 0,
          "url": ""
        }
      ],
      "summary": "",
      "url": ""
    },
    {
      "id": "evt-25000000",
      "title": "超250万人请愿将阿根廷逐出世界杯",
      "category": "society",
      "hotScore": 0.6375,
      "freshness": 1,
      "crossSource": 0.6309,
      "totalScore": 0.7443,
      "sources": [
        {
          "channel": "toutiao",
          "rank": 6,
          "hot": 16858071,
          "url": "https://www.toutiao.com/trending/7661817781495447579/"
        }
      ],
      "summary": "",
      "url": "https://www.toutiao.com/trending/7661817781495447579/"
    },
    {
      "id": "evt-3d000000",
      "title": "好未来《熊猫博士》3D动画片登陆央视少儿频道",
      "category": "society",
      "hotScore": 0.63,
      "freshness": 1,
      "crossSource": 0.6309,
      "totalScore": 0.7413,
      "sources": [
        {
          "channel": "36kr",
          "rank": 7,
          "hot": 0,
          "url": ""
        }
      ],
      "summary": "36氪获悉，自4月9日起，中央电视台少儿频道携手好未来旗下教育品牌熊猫博士上线3D系列动画片《熊猫博士》。与此同时，《熊猫博士》3D动画片也在美国、加拿大、俄罗斯、意大利等多个国家、地区陆续发行，并登陆Discovery探索频道等多个世界知名节目。",
      "url": ""
    },
    {
      "id": "evt-80000000",
      "title": "总理座谈会于东来等8人成“座上宾”",
      "category": "society",
      "hotScore": 0.6,
      "freshness": 1,
      "crossSource": 0.6309,
      "totalScore": 0.7293,
      "sources": [
        {
          "channel": "baidu",
          "rank": 6,
          "hot": 0,
          "url": "https://m.baidu.com/s?word=%E6%80%BB%E7%90%86%E5%BA%A7%E8%B0%88%E4%BC%9A%E4%BA%8E%E4%B8%9C%E6%9D%A5%E7%AD%898%E4%BA%BA%E6%88%90%E2%80%9C%E5%BA%A7%E4%B8%8A%E5%AE%BE%E2%80%9D&sa=fyb_news"
        }
      ],
      "summary": "",
      "url": "https://m.baidu.com/s?word=%E6%80%BB%E7%90%86%E5%BA%A7%E8%B0%88%E4%BC%9A%E4%BA%8E%E4%B8%9C%E6%9D%A5%E7%AD%898%E4%BA%BA%E6%88%90%E2%80%9C%E5%BA%A7%E4%B8%8A%E5%AE%BE%E2%80%9D&sa=fyb_news"
    },
    {
      "id": "evt-93000000",
      "title": "法男子来华给93岁母亲背回一台空调",
      "category": "society",
      "hotScore": 0.595,
      "freshness": 1,
      "crossSource": 0.6309,
      "totalScore": 0.7273,
      "sources": [
        {
          "channel": "toutiao",
          "rank": 7,
          "hot": 15253813,
          "url": "https://www.toutiao.com/trending/7662002513113251890/"
        }
      ],
      "summary": "",
      "url": "https://www.toutiao.com/trending/7662002513113251890/"
    }
  ]
}